zmxtools/__init__.py
zmxtools/cli.py
zmxtools/py.typed
zmxtools/zar.py
zmxtools-0.1.5.dist-info/LICENSE
zmxtools-0.1.5.dist-info/METADATA
zmxtools-0.1.5.dist-info/WHEEL
zmxtools-0.1.5.dist-info/entry_points.txt
zmxtools-0.1.5.dist-info/RECORD
