Metadata-Version: 2.1
Name: zmxtools
Version: 0.1.5
Summary: Toolkit to read Zemax OpticStudio files.
Home-page: https://github.com/tttom/zmxtools
License: AGPL3
Keywords: Optical Design,Lens Design,Zemax,Zemax Archive (ZAR)
Author: Tom Vettenburg
Author-email: tom.vettenburg@gmail.com
Requires-Python: >=3.8,<4.0
Classifier: Development Status :: 4 - Beta
Classifier: Intended Audience :: Science/Research
Classifier: License :: OSI Approved :: GNU Affero General Public License v3
Classifier: License :: Other/Proprietary License
Classifier: Operating System :: OS Independent
Classifier: Programming Language :: Python :: 3
Classifier: Programming Language :: Python :: 3.8
Classifier: Programming Language :: Python :: 3.9
Classifier: Programming Language :: Python :: 3.10
Classifier: Programming Language :: Python :: 3.11
Classifier: Programming Language :: Python :: 3
Classifier: Topic :: Scientific/Engineering :: Physics
Provides-Extra: docs
Requires-Dist: coloredlogs (>=15.0.1,<16.0.0) ; extra == "docs"
Requires-Dist: importlib_metadata (>=4.11,<5.0) ; python_version >= "3.7" and python_version < "3.8"
Requires-Dist: m2r2 (>=0.3.2,<0.4.0) ; extra == "docs"
Requires-Dist: sphinx (>=5.3,<6.0) ; extra == "docs"
Requires-Dist: sphinx-autodoc-typehints (>=1.22,<2.0) ; extra == "docs"
Requires-Dist: sphinx_rtd_theme (>=1.2,<2.0) ; extra == "docs"
Requires-Dist: tomlkit (>=0.10,<0.11) ; extra == "docs"
Project-URL: Repository, https://github.com/tttom/zmxtools
